customs_id_number/__init__.py
customs_id_number/customs_id_number.py
customs_id_number_validator-0.2.9.1.dist-info/LICENSE
customs_id_number_validator-0.2.9.1.dist-info/METADATA
customs_id_number_validator-0.2.9.1.dist-info/WHEEL
customs_id_number_validator-0.2.9.1.dist-info/entry_points.txt
customs_id_number_validator-0.2.9.1.dist-info/top_level.txt
customs_id_number_validator-0.2.9.1.dist-info/RECORD
